lir-1.3.1.dist-info/METADATA
lir-1.3.1.dist-info/WHEEL
lir-1.3.1.dist-info/entry_points.txt
lir-1.3.1.dist-info/licenses/LICENSE.txt
lir/__init__.py
lir/aggregation.py
lir/algorithms/__init__.py
lir/algorithms/bayeserror.py
lir/algorithms/bootstraps.py
lir/algorithms/invariance_bounds.py
lir/algorithms/isotonic_regression.py
lir/algorithms/kde.py
lir/algorithms/llr_overestimation.py
lir/algorithms/logistic_regression.py
lir/algorithms/percentile_rank.py
lir/bounding.py
lir/config/__init__.py
lir/config/base.py
lir/config/data_providers.py
lir/config/data_strategies.py
lir/config/experiment_strategies.py
lir/config/lrsystem_architectures.py
lir/config/metrics.py
lir/config/substitution.py
lir/config/transform.py
lir/config/util.py
lir/data/data_strategies.py
lir/data/datasets/alcohol_breath_analyser.py
lir/data/datasets/feature_data_csv.py
lir/data/datasets/glass.py
lir/data/datasets/synthesized_normal_binary.py
lir/data/datasets/synthesized_normal_multiclass.py
lir/data/io.py
lir/data/models.py
lir/experiment.py
lir/lrsystems/__init__.py
lir/lrsystems/binary_lrsystem.py
lir/lrsystems/lrsystems.py
lir/lrsystems/score_based.py
lir/lrsystems/two_level.py
lir/main.py
lir/metrics/__init__.py
lir/metrics/devpav.py
lir/metrics/overestimation.py
lir/optuna.py
lir/persistence.py
lir/plotting/__init__.py
lir/plotting/expected_calibration_error.py
lir/registry.py
lir/resources/__init__.py
lir/resources/registry.yaml
lir/transform/__init__.py
lir/transform/distance.py
lir/transform/pairing.py
lir/transform/pipeline.py
lir/util.py
lir/visualization.py
lir-1.3.1.dist-info/RECORD
