Metadata-Version: 2.1
Name: lir
Version: 1.3.1
Summary: Package for optimising and evaluating Likelihood Ratio (LR) systems.
Author-Email: Netherlands Forensics Institute <netherlandsforensicinstitute@users.noreply.github.com>
License: Apache Software License 2.0
Project-URL: homepage, https://github.com/NetherlandsForensicInstitute/lir/
Requires-Python: >=3.11
Requires-Dist: confidence>=0.17.1
Requires-Dist: matplotlib>=3.5
Requires-Dist: numpy>=1.22
Requires-Dist: scikit-learn>=1.2
Requires-Dist: tqdm>=4.67.1
Requires-Dist: optuna>=4.4.0
Requires-Dist: scipy>=1.13.1
Requires-Dist: pandas>=2.3.2
Requires-Dist: KDEpy>=1.1.12
Requires-Dist: pydantic>=2.12.3
